[{"ruleExplore":{},"bookSourceType":0,"ruleSearch":{"author":"class.btm@tag.a@title","bookList":"class.item","wordCount":"class.orange visible-xs@text","intro":"tag.dd@text","coverUrl":"class.lazy@data-original","kind":"class.blue visible-xs@text","bookUrl":"class.image@tag.a@href","name":"class.image@tag.a@title"},"ruleBookInfo":{},"respondTime":180000,"ruleContent":{"content":"id.booktxt@html","nextContentUrl":"text.下一页@href"},"searchUrl":"\/so\/,{\n\"method\": \"post\",\n\"body\": \"searchkey={{key}}\"}","weight":60,"enabledExplore":true,"header":"{\n    \"User-Agent\": \"Mozilla\/5.0 (iPhone; CPU iPhone OS 16_1_2 like Mac OS X) AppleWebKit\/605.1.15 (KHTML, like Gecko) Version\/16.1.2 Mobile\/15E148 Safari\/604.1\",\n    \"Accept-Language\":\"zh-CN,zh;q=0.9\"\n}","ruleToc":{"chapterName":"tag.dd@text","chapterUrl":"href","chapterList":".box_con dl a"},"enabled":true,"bookSourceUrl":"https:\/\/www.83zws.com\/","lastUpdateTime":0,"bookSourceName":"八三中文","bookSourceGroup":"自写书源","exploreUrl":"小说排行::\/rank\/allvisit\/\n玄幻魔法::\/sort\/1_{{page}}\/\n武侠修真::\/sort\/2_{{page}}\/\n都市言情::\/sort\/3_{{page}}\/\n历史军事::\/sort\/4_{{page}}\/\n科幻灵异::\/sort\/5_{{page}}\/\n游戏竞技::\/sort\/6_{{page}}\/\n女生频道::\/sort\/7_{{page}}\/","customOrder":0}]